[{"id":261492,"first_name":"Shawn","last_name":"Robertson","game_count":76342,"img_src":"images/src/cover.jpg"},
{"id":404964,"first_name":"Bobby","last_name":"Richardson","game_count":39100,"img_src":"images/src/cover.jpg"},
{"id":757461,"first_name":"Melissa","last_name":"Morris","game_count":16026,"img_src":"images/src/cover.jpg"},
{"id":845368,"first_name":"Ryan","last_name":"Black","game_count":75902,"img_src":"images/src/cover.jpg"},
{"id":599454,"first_name":"Paul","last_name":"Ortiz","game_count":15150,"img_src":"images/src/cover.jpg"},
{"id":561510,"first_name":"Nicole","last_name":"King","game_count":67404,"img_src":"images/src/cover.jpg"},
{"id":526632,"first_name":"Elizabeth","last_name":"Kim","game_count":34613,"img_src":"images/src/cover.jpg"},
{"id":868561,"first_name":"Rebecca","last_name":"Boyd","game_count":77315,"img_src":"images/src/cover.jpg"},
{"id":886884,"first_name":"Ruth","last_name":"Romero","game_count":62837,"img_src":"images/src/cover.jpg"},
{"id":433671,"first_name":"Marilyn","last_name":"Williamson","game_count":60368,"img_src":"images/src/cover.jpg"},
{"id":404132,"first_name":"Larry","last_name":"Johnston","game_count":48498,"img_src":"images/src/cover.jpg"},
{"id":982297,"first_name":"James","last_name":"Allen","game_count":89985,"img_src":"images/src/cover.jpg"},
{"id":423321,"first_name":"Tammy","last_name":"Sims","game_count":16598,"img_src":"images/src/cover.jpg"},
{"id":718221,"first_name":"Kathy","last_name":"Cole","game_count":7338,"img_src":"images/src/cover.jpg"},
{"id":280656,"first_name":"Ashley","last_name":"Welch","game_count":98002,"img_src":"images/src/cover.jpg"},
{"id":871658,"first_name":"Sean","last_name":"Diaz","game_count":74464,"img_src":"images/src/cover.jpg"},
{"id":888248,"first_name":"Kevin","last_name":"Carpenter","game_count":92495,"img_src":"images/src/cover.jpg"},
{"id":573537,"first_name":"Shawn","last_name":"Fowler","game_count":69422,"img_src":"images/src/cover.jpg"},
{"id":227356,"first_name":"Irene","last_name":"Ford","game_count":65299,"img_src":"images/src/cover.jpg"},
{"id":954680,"first_name":"Jane","last_name":"West","game_count":82769,"img_src":"images/src/cover.jpg"}]